README.md
setup.py
cloudlab/__init__.py
cloudlab/commandline.py
cloudlab.egg-info/PKG-INFO
cloudlab.egg-info/SOURCES.txt
cloudlab.egg-info/dependency_links.txt
cloudlab.egg-info/entry_points.txt
cloudlab.egg-info/requires.txt
cloudlab.egg-info/top_level.txt
cloudlab/plans/aws_with_subnets.yaml.j2
cloudlab/resources/cloudlab_config.yaml