Metadata-Version: 2.1
Name: cloudlab
Version: 1.2.0
Summary: A tool for quickly provisioning lab environments on AWS.
Home-page: https://github.com/wrmay/cloudlab
Author: Randy May
License: MIT
Requires-Dist: jinja2>=3.1.4
Requires-Dist: PyYaml>=6.0.2
